<databaseChangeLog
        xmlns="http://www.liquibase.org/xml/ns/dbchangelog"
        xmlns:xsi="http://www.w3.org/2001/XMLSchema-instance"
        xmlns:ext="http://www.liquibase.org/xml/ns/dbchangelog-ext"
        xsi:schemaLocation="http://www.liquibase.org/xml/ns/dbchangelog http://www.liquibase.org/xml/ns/dbchangelog/dbchangelog-3.1.xsd
    http://www.liquibase.org/xml/ns/dbchangelog-ext http://www.liquibase.org/xml/ns/dbchangelog/dbchangelog-ext.xsd">

    <changeSet id="3" author="karol">
        <addColumn tableName="user">
            <column name="creation_time" type="timestamp" defaultValue="2013-09-29">
                <constraints nullable="false"/>
            </column>
        </addColumn>
        <addColumn tableName="follow">
            <column name="creation_time" type="timestamp" defaultValue="2013-09-29">
                <constraints nullable="false"/>
            </column>
        </addColumn>
    </changeSet>

</databaseChangeLog>